vectorObjects/DefinedVectors.py
vectorObjects/VectorMaster.py
vectorObjects/__init__.py
vectorObjects-0.7.2.dist-info/LICENSE
vectorObjects-0.7.2.dist-info/METADATA
vectorObjects-0.7.2.dist-info/WHEEL
vectorObjects-0.7.2.dist-info/top_level.txt
vectorObjects-0.7.2.dist-info/RECORD
